cosmodocs-0.2.6.dist-info/METADATA
cosmodocs-0.2.6.dist-info/WHEEL
cosmodocs/__init__.py
cosmodocs-0.2.6.dist-info/RECORD
