Metadata-Version: 2.1
Name: CosmoDocs
Version: 0.2.6
Summary: A file based documentation generator for Python projects.
Author-Email: Thiago Santa Clara <strovsk@outlook.com>
License: MIT
Requires-Python: >=3.9
